originec/__init__.py
originec/__main__.py
originec/Biologic/__init__.py
originec/Biologic/cellpy_debug.log
originec/Biologic/cellpy_info.log
originec/Biologic/chdis_bio.py
originec/CV/__init__.py
originec/CV/Biologic.py
originec/CV/cvorigin.py
originec/CV/Gamry.py
originec/origin_UI.py
originec-0.1.4.dist-info/entry_points.txt
originec-0.1.4.dist-info/METADATA
originec-0.1.4.dist-info/WHEEL
originec-0.1.4.dist-info/RECORD
