Metadata-Version: 2.4
Name: originec
Version: 0.1.4
Summary: Electrochemical data processing for OriginPro
Author: tomooki
Author-email: tomooki0414@gmail.com
Requires-Python: >=3.11
Classifier: Programming Language :: Python :: 3
Classifier: Programming Language :: Python :: 3.11
Classifier: Programming Language :: Python :: 3.12
Classifier: Programming Language :: Python :: 3.13
Classifier: Programming Language :: Python :: 3.14
Requires-Dist: freesimplegui (>=5.2.0.post1,<6.0.0)
Requires-Dist: numpy (>=2.4.1,<3.0.0)
Requires-Dist: originpro (>=1.1.14,<2.0.0)
Requires-Dist: pandas (>=2.3.3,<3.0.0)
Requires-Dist: scipy (>=1.17.0,<2.0.0)
